MANIFEST.in
README.md
setup.py
raise_if/__init__.py
raise_if.egg-info/PKG-INFO
raise_if.egg-info/SOURCES.txt
raise_if.egg-info/dependency_links.txt
raise_if.egg-info/top_level.txt