Metadata-Version: 1.1
Name: raise-if
Version: 0.1.3
Summary: Probably the small python package, only includes raise_if function
Home-page: https://github.com/rochacbruno/raise_if
Author: Bruno Rocha
Author-email: rochacbruno@gmail.com
License: UNKNOWN
Platform: UNKNOWN
Classifier: Development Status :: 2 - Pre-Alpha
Classifier: Programming Language :: Python
Classifier: Programming Language :: Python :: 2
Classifier: Programming Language :: Python :: 2.7
Classifier: Programming Language :: Python :: 3
Classifier: Programming Language :: Python :: 3.3
